{
  "$schema" : "https://json-schema.axonivy.com/data-class/12.0.0/data-class.json",
  "simpleName" : "UploadByCallSubprocessData",
  "namespace" : "com.axonivy.connector.azure.blob.demo.UploadByCallSubprocess",
  "isBusinessCaseData" : false,
  "fields" : [ {
    "name" : "bean",
    "type" : "com.axonivy.connector.azure.blob.demo.bean.UploadByCallSubprocess"
  }, {
    "name" : "link",
    "type" : "String"
  }, {
    "name" : "isSuccess",
    "type" : "Boolean"
  }, {
    "name" : "isExist",
    "type" : "Boolean"
  }, {
    "name" : "combineFileNameAndFolder",
    "type" : "String"
  } ]
}